pubgSearch/__init__.py
pubgSearch/pubg_auth.py
pubgSearch/pubg_data.py
pubgSearch-1.1.dist-info/METADATA
pubgSearch-1.1.dist-info/RECORD
pubgSearch-1.1.dist-info/WHEEL
pubgSearch-1.1.dist-info/top_level.txt
